LICENSE
MANIFEST.in
README.md
requirements.txt
setup.py
dhtc_server/__init__.py
dhtc_server/__main__.py
dhtc_server.egg-info/PKG-INFO
dhtc_server.egg-info/SOURCES.txt
dhtc_server.egg-info/dependency_links.txt
dhtc_server.egg-info/entry_points.txt
dhtc_server.egg-info/requires.txt
dhtc_server.egg-info/top_level.txt
dhtc_server/enums/SearchMode.py
dhtc_server/enums/SearchType.py
dhtc_server/enums/__init__.py
dhtc_server/models/BlacklistItem.py
dhtc_server/models/Torrent.py
dhtc_server/models/User.py
dhtc_server/models/Watch.py
dhtc_server/models/__init__.py
dhtc_server/models/requests/AddTorrentRequest.py
dhtc_server/models/requests/SearchRequest.py
dhtc_server/models/requests/SearchTorrentRequest.py
dhtc_server/models/requests/__init__.py
dhtc_server/models/responses/AddTorrentResponse.py
dhtc_server/models/responses/SearchTorrentResponse.py
dhtc_server/models/responses/TorrentCountResponse.py
dhtc_server/models/responses/__init__.py
dhtc_server/routes/__init__.py
dhtc_server/routes/api/__init__.py
dhtc_server/routes/api/blacklist.py
dhtc_server/routes/api/torrents.py
dhtc_server/routes/api/users.py
dhtc_server/routes/api/watches.py
dhtc_server/routes/ui/__init__.py
dhtc_server/routes/ui/blacklist.py
dhtc_server/routes/ui/dashboard.py
dhtc_server/routes/ui/discover.py
dhtc_server/routes/ui/search.py
dhtc_server/routes/ui/torrent.py
dhtc_server/routes/ui/watches.py
dhtc_server/routes/ui/settings/__init__.py
dhtc_server/routes/ui/settings/clients.py
dhtc_server/routes/ui/settings/database.py
dhtc_server/routes/ui/settings/indexing.py
dhtc_server/routes/ui/settings/telegram.py
dhtc_server/routes/ui/settings/users.py
dhtc_server/static/css/halfmoon.min.css
dhtc_server/static/js/chart.js
dhtc_server/static/js/common.js
dhtc_server/static/js/halfmoon.min.js
dhtc_server/static/js/livechart.js
dhtc_server/templates/base.html
dhtc_server/templates/blacklist.html
dhtc_server/templates/dashboard.html
dhtc_server/templates/discover.html
dhtc_server/templates/login.html
dhtc_server/templates/result_table.html
dhtc_server/templates/search.html
dhtc_server/templates/settings.html
dhtc_server/templates/settings_clients.html
dhtc_server/templates/settings_database.html
