Metadata-Version: 2.1
Name: dhtc-server
Version: 2.0.5
Summary: distributed hash table crawler ui and api server
Home-page: https://github.com/nbdy/dhtc-server
Author: Pascal Eberlein
Author-email: pascal@eberlein.io
License: UNKNOWN
Keywords: dhtc server
Platform: UNKNOWN
Classifier: Intended Audience :: Developers
Classifier: Topic :: Software Development :: Build Tools
Classifier: License :: OSI Approved :: MIT License
License-File: LICENSE
